xmimsim/__init__.py
xmimsim/func.py
xmimsim/strings.py
xmimsim/version.py
xmimsim/xmimsim.py
xmimsim-0.1.3.dist-info/LICENCE.txt
xmimsim-0.1.3.dist-info/METADATA
xmimsim-0.1.3.dist-info/WHEEL
xmimsim-0.1.3.dist-info/top_level.txt
xmimsim-0.1.3.dist-info/RECORD
