Metadata-Version: 2.1
Name: xmimsim
Version: 0.1.3
Summary: Toolkit for making and processing X-ray fluoresence simulations via XMI-MSIM
Home-page: UNKNOWN
Author: NGeorgescu
License: see LICENSE.txt
Keywords: xmimsim xmi msim xrf fluorescence x-ray xray simulation
Platform: UNKNOWN
